promnesia/__init__.py
promnesia/__main__.py
promnesia/cannon.py
promnesia/common.py
promnesia/compare.py
promnesia/compat.py
promnesia/config.py
promnesia/extract.py
promnesia/logging.py
promnesia/py.typed
promnesia/server.py
promnesia/sqlite.py
promnesia/database/common.py
promnesia/database/dump.py
promnesia/database/load.py
promnesia/misc/__init__.pyi
promnesia/misc/config_example.py
promnesia/misc/install_server.py
promnesia/sources/auto.py
promnesia/sources/auto_logseq.py
promnesia/sources/auto_obsidian.py
promnesia/sources/browser.py
promnesia/sources/browser_legacy.py
promnesia/sources/demo.py
promnesia/sources/fbmessenger.py
promnesia/sources/filetypes.py
promnesia/sources/github.py
promnesia/sources/guess.py
promnesia/sources/hackernews.py
promnesia/sources/hpi.py
promnesia/sources/html.py
promnesia/sources/hypothesis.py
promnesia/sources/instapaper.py
promnesia/sources/markdown.py
promnesia/sources/org.py
promnesia/sources/plaintext.py
promnesia/sources/pocket.py
promnesia/sources/reddit.py
promnesia/sources/roamresearch.py
promnesia/sources/rss.py
promnesia/sources/shellcmd.py
promnesia/sources/signal.py
promnesia/sources/smscalls.py
promnesia/sources/stackexchange.py
promnesia/sources/takeout.py
promnesia/sources/takeout_legacy.py
promnesia/sources/telegram.py
promnesia/sources/telegram_legacy.py
promnesia/sources/twitter.py
promnesia/sources/vcs.py
promnesia/sources/viber.py
promnesia/sources/website.py
promnesia/sources/zulip.py
promnesia/tests/__init__.py
promnesia/tests/common.py
promnesia/tests/server_helper.py
promnesia/tests/test_cannon.py
promnesia/tests/test_cli.py
promnesia/tests/test_compare.py
promnesia/tests/test_config.py
promnesia/tests/test_db_dump.py
promnesia/tests/test_extract.py
promnesia/tests/test_extract_urls.py
promnesia/tests/test_indexer.py
promnesia/tests/test_server.py
promnesia/tests/test_traverse.py
promnesia/tests/utils.py
promnesia/tests/sources/__init__.py
promnesia/tests/sources/test_auto.py
promnesia-1.5.20251011.dist-info/METADATA
promnesia-1.5.20251011.dist-info/WHEEL
promnesia-1.5.20251011.dist-info/entry_points.txt
promnesia-1.5.20251011.dist-info/licenses/LICENSE
promnesia-1.5.20251011.dist-info/RECORD
