Metadata-Version: 2.4
Name: promnesia
Version: 1.5.20251011
Summary: Enhancement of your browsing history
Project-URL: Homepage, https://github.com/karlicoss/promnesia
Author-email: "Dima Gerasimov (@karlicoss)" <karlicoss@gmail.com>
Maintainer-email: "Dima Gerasimov (@karlicoss)" <karlicoss@gmail.com>
License: MIT License
License-File: LICENSE
Requires-Python: >=3.12
Requires-Dist: more-itertools
Requires-Dist: platformdirs
Requires-Dist: promnesia[indexer]
Requires-Dist: promnesia[server]
Requires-Dist: sqlalchemy>=2.0
Requires-Dist: typing-extensions
Requires-Dist: tzlocal
Provides-Extra: all
Requires-Dist: beautifulsoup4; extra == 'all'
Requires-Dist: fastapi; extra == 'all'
Requires-Dist: hpi; extra == 'all'
Requires-Dist: logzero; extra == 'all'
Requires-Dist: lxml; extra == 'all'
Requires-Dist: mistletoe; extra == 'all'
Requires-Dist: orgparse>=0.3.0; extra == 'all'
Requires-Dist: python-magic; extra == 'all'
Requires-Dist: urlextract; extra == 'all'
Requires-Dist: uvicorn[standard]; extra == 'all'
Provides-Extra: hpi
Requires-Dist: hpi; extra == 'hpi'
Provides-Extra: html
Requires-Dist: beautifulsoup4; extra == 'html'
Requires-Dist: lxml; extra == 'html'
Provides-Extra: indexer
Requires-Dist: urlextract; extra == 'indexer'
Provides-Extra: markdown
Requires-Dist: mistletoe; extra == 'markdown'
Provides-Extra: optional
Requires-Dist: logzero; extra == 'optional'
Requires-Dist: python-magic; extra == 'optional'
Provides-Extra: org
Requires-Dist: orgparse>=0.3.0; extra == 'org'
Provides-Extra: server
Requires-Dist: fastapi; extra == 'server'
Requires-Dist: uvicorn[standard]; extra == 'server'
Provides-Extra: telegram
